jupyter_cassini_server/__init__.py
jupyter_cassini_server/_version.py
jupyter_cassini_server/handlers.py
jupyter_cassini_server/safety.py
jupyter_cassini_server/serialisation.py
jupyter_cassini_server/schema/models.py
jupyter_cassini_server/tests/__init__.py
jupyter_cassini_server/tests/test_handlers.py
jupyter_cassini_server/tests/test_safety.py
jupyter_cassini_server/tests/project/cas_project.py
jupyter_cassini_server-0.3.1.data/data/etc/jupyter/jupyter_notebook_config.d/jupyter_cassini_server.json
jupyter_cassini_server-0.3.1.data/data/etc/jupyter/jupyter_server_config.d/jupyter_cassini_server.json
jupyter_cassini_server-0.3.1.data/data/share/jupyter/labextensions/jupyter_cassini/package.json
jupyter_cassini_server-0.3.1.data/data/share/jupyter/labextensions/jupyter_cassini/static/145.bd2d1525ee6818b02947.js
jupyter_cassini_server-0.3.1.data/data/share/jupyter/labextensions/jupyter_cassini/static/145.bd2d1525ee6818b02947.js.LICENSE.txt
jupyter_cassini_server-0.3.1.data/data/share/jupyter/labextensions/jupyter_cassini/static/282.3a5726f3fd2523a0c010.js
jupyter_cassini_server-0.3.1.data/data/share/jupyter/labextensions/jupyter_cassini/static/477.98fa731df9550fb3d78f.js
jupyter_cassini_server-0.3.1.data/data/share/jupyter/labextensions/jupyter_cassini/static/487.6160221fe58b43d8b532.js
jupyter_cassini_server-0.3.1.data/data/share/jupyter/labextensions/jupyter_cassini/static/541.83177c6f021846fbefc7.js
jupyter_cassini_server-0.3.1.data/data/share/jupyter/labextensions/jupyter_cassini/static/554.42aec4a502e2fe620beb.js
jupyter_cassini_server-0.3.1.data/data/share/jupyter/labextensions/jupyter_cassini/static/581.b09dd59682054b30b829.js
jupyter_cassini_server-0.3.1.data/data/share/jupyter/labextensions/jupyter_cassini/static/598.19a7a6b735a8e128900f.js
jupyter_cassini_server-0.3.1.data/data/share/jupyter/labextensions/jupyter_cassini/static/695.49a2667279fa2954ada6.js
jupyter_cassini_server-0.3.1.dist-info/METADATA
jupyter_cassini_server-0.3.1.dist-info/WHEEL
jupyter_cassini_server-0.3.1.dist-info/licenses/LICENSE
jupyter_cassini_server-0.3.1.dist-info/RECORD
