Metadata-Version: 2.4
Name: jupyter_cassini_server
Version: 0.3.1
Dynamic: Keywords
Summary: Jupyterlab extension for interacting with Cassini projects
Project-URL: Homepage, https://github.com/github_username/jupyter_cassini_server
Project-URL: Bug Tracker, https://github.com/github_username/jupyter_cassini_server/issues
Project-URL: Repository, https://github.com/github_username/jupyter_cassini_server.git
Author-email: Hugh Ramsden <hugh.o.ramsden@gmail.com>
License:                     GNU GENERAL PUBLIC LICENSE
License-File: LICENSE
Classifier: Framework :: Jupyter
Classifier: Framework :: Jupyter :: JupyterLab
Classifier: Framework :: Jupyter :: JupyterLab :: 4
Classifier: Framework :: Jupyter :: JupyterLab :: Extensions
Classifier: Framework :: Jupyter :: JupyterLab :: Extensions :: Prebuilt
Classifier: License :: OSI Approved :: BSD License
Classifier: Programming Language :: Python
Classifier: Programming Language :: Python :: 3
Classifier: Programming Language :: Python :: 3.8
Classifier: Programming Language :: Python :: 3.9
Classifier: Programming Language :: Python :: 3.10
Classifier: Programming Language :: Python :: 3.11
Requires-Python: >=3.8
Requires-Dist: cassini<4,>=0.2.0a5
Requires-Dist: jupyter-server<3,>=2.0.1
Requires-Dist: numpy<2,>=1.0
Provides-Extra: test
Requires-Dist: coverage; extra == 'test'
Requires-Dist: datamodel-code-generator; extra == 'test'
Requires-Dist: pytest; extra == 'test'
Requires-Dist: pytest-asyncio; extra == 'test'
Requires-Dist: pytest-cov; extra == 'test'
Requires-Dist: pytest-jupyter[server]>=0.6.0; extra == 'test'
